{
  "调动": {
    "type": "python_script",
    "description": "调动：执行Python脚本完成操作",
    "has_multi_coords": false,
    "has_auto_input": true,
    "is_python_template": true,
    "python_code": "import os\nimport time\nimport pyautogui\nimport numpy as np\nimport cv2\n\nprint(\"=\"*50)\nprint(\"【调动模块】开始执行\")\nprint(\"=\"*50)\n\nworkgroup_id = '{{workgroup_id}}'\ncoord_params = '{{coord_params}}'\n\nprimary_pic_dir = os.path.join(os.path.dirname(os.path.abspath(__file__)), '3MCWB', 'workgroups', workgroup_id)\nsecondary_pic_dir = os.path.join(os.path.dirname(os.path.abspath(__file__)), '3MCWB', 'pic')\n\nprint(f\"[DEBUG] workgroup_id={workgroup_id}\")\nprint(f\"[DEBUG] primary_pic_dir={primary_pic_dir}\")\nprint(f\"[DEBUG] secondary_pic_dir={secondary_pic_dir}\")\n\ndef find_image_click(image_name, wait_time=1):\n    image_path = None\n    path1 = os.path.join(primary_pic_dir, image_name)\n    print(f\"[DEBUG] path1={path1}, exists={os.path.exists(path1)}\")\n    if os.path.exists(path1):\n        image_path = path1\n        print(f\"[图片查找] 找到文件: {path1}\")\n    if not image_path:\n        path2 = os.path.join(secondary_pic_dir, image_name)\n        print(f\"[DEBUG] path2={path2}, exists={os.path.exists(path2)}\")\n        if os.path.exists(path2):\n            image_path = path2\n            print(f\"[图片查找] 找到文件(备用路径): {path2}\")\n    if not image_path:\n        print(f\"[图片查找] 未找到图片: {image_name}\")\n        return False\n    print(f'[图片查找] 查找图片: {image_name}')\n    screenshot = pyautogui.screenshot()\n    screen_np = np.array(screenshot)\n    screen_cv2 = cv2.cvtColor(screen_np, cv2.COLOR_RGB2BGR)\n    template = cv2.imread(image_path)\n    if template is None:\n        print(f'[图片查找] 无法读取图片: {image_name}')\n        return False\n    result = cv2.matchTemplate(screen_cv2, template, cv2.TM_CCOEFF_NORMED)\n    min_val, max_val, min_loc, max_loc = cv2.minMaxLoc(result)\n    if max_val >= 0.8:\n        h, w = template.shape[:2]\n        center_x = max_loc[0] + w // 2\n        center_y = max_loc[1] + h // 2\n        print(f'[图片查找] 找到图片 {image_name}，坐标: ({center_x}, {center_y})')\n        pyautogui.click(center_x, center_y)\n        print(f'[图片查找] 点击坐标: ({center_x}, {center_y})')\n        if wait_time > 0:\n            print(f'[图片查找] 等待 {wait_time} 秒...')\n            time.sleep(wait_time)\n        return True\n    else:\n        print(f'[图片查找] 未找到图片 {image_name}，相似度: {max_val:.3f}')\n        return False\n\nfound_any = find_image_click('1-ST.png', 0) or find_image_click('1-FD.png', 0) or find_image_click('1-HC.png', 0)\n\nif found_any:\n    print(\"[条件成立] 找到1-ST/1-FD/1-HC图片，执行2.1-2.36操作\")\n    print(\"[2.1] 点击坐标36,522\")\n    pyautogui.click(36, 522)\n    time.sleep(1)\n    print(\"[2.2] 等待1秒\")\n    print(\"[2.3] 点击坐标36,522\")\n    pyautogui.click(36, 522)\n    time.sleep(1)\n    print(\"[2.4] 等待1秒\")\n    print(\"[2.5] 点击坐标36,522\")\n    pyautogui.click(36, 522)\n    time.sleep(1)\n    print(\"[2.6] 等待1秒\")\n    print(\"[2.7] 点击坐标36,522\")\n    pyautogui.click(36, 522)\n    time.sleep(1)\n    print(\"[2.8] 等待1秒\")\n    print(\"[2.9] 点击坐标36,522\")\n    pyautogui.click(36, 522)\n    time.sleep(1)\n    print(\"[2.10] 等待1秒\")\n    print(\"[2.11] 点击坐标36,522\")\n    pyautogui.click(36, 522)\n    time.sleep(1)\n    print(\"[2.12] 等待1秒\")\n    print(\"[2.13] 点击坐标955,715\")\n    pyautogui.click(955, 715)\n    time.sleep(1)\n    print(\"[2.14] 等待1秒\")\n    print(f\"[键盘输入] 使用pynput.keyboard输入参数: {coord_params}\")\n    from pynput.keyboard import Controller\n    kb = Controller()\n    kb.type(coord_params)\n    time.sleep(1)\n    print(\"[2.21] 点击坐标1240,708\")\n    pyautogui.click(1240, 708)\n    time.sleep(1)\n    print(\"[2.22] 等待1秒\")\n    print(\"[2.23] 点击坐标1158,718\")\n    pyautogui.click(1158, 718)\n    time.sleep(2)\n    print(\"[2.24] 等待2秒\")\n    print(\"[2.25] 点击坐标666,386\")\n    pyautogui.click(666, 386)\n    time.sleep(1)\n    print(\"[2.26] 等待1秒\")\n    find_image_click('8-ZS.png', 1)\n    time.sleep(1)\n    find_image_click('8-ZS.png', 1)\n    time.sleep(1)\n    print(\"[2.32] 等待1秒\")\n    if find_image_click('1-CZ.png', 1):\n        print(\"[标记] 已找到1-CZ.png并点击，命令执行成功，退出脚本\")\n        print(\"=\"*50)\n        print(\"【模块】执行完成!\")\n        print(\"=\"*50)\n        raise SystemExit(0)\n    time.sleep(1)\n    print(\"[2.34] 等待1秒\")\n    if find_image_click('1-CZ.png', 1):\n        print(\"[标记] 已找到1-CZ.png并点击，命令执行成功，退出脚本\")\n        print(\"=\"*50)\n        print(\"【模块】执行完成!\")\n        print(\"=\"*50)\n        raise SystemExit(0)\n    time.sleep(1)\n    print(\"[2.34] 等待1秒\")\nelse:\n    print(\"[条件不成立] 未找到1-ST/1-FD/1-HC图片，执行2.37-2.43操作\")\n    print(\"[2.37] 点击坐标67,700\")\n    pyautogui.click(67, 700)\n    time.sleep(2)\n    print(\"[2.38] 等待2秒\")\n    find_image_click('1-TC.png', 4)\n    time.sleep(1)\n    print(\"[2.40] 等待1秒\")\n    find_image_click('1-TC.png', 1)\n    time.sleep(1)\n    print(\"[2.42] 等待1秒\")\n    find_image_click('1-CC.png', 4)\n\nprint(\"=\"*50)\nprint(\"【模块】执行完成!\")\nprint(\"=\"*50)",
    "template": {
      "coords": [
        {
          "x": 0,
          "y": 0,
          "label": "坐标参数(格式0.0)"
        }
      ],
      "workflows": [],
      "exec_mode": "immediate"
    }
  },
  "走到": {
    "type": "python_script",
    "description": "走到：点击指定坐标并执行工作流",
    "has_multi_coords": false,
    "has_auto_input": false,
    "is_python_template": true,
    "python_code": "import os\nimport time\nimport pyautogui\nimport numpy as np\nimport cv2\n\nprint(\"=\"*50)\nprint(\"【走到模块】开始执行\")\nprint(\"=\"*50)\n\nworkgroup_id = '{{workgroup_id}}'\ncoord_params = '{{coord_params}}'\n\nprimary_pic_dir = os.path.join(os.path.dirname(os.path.abspath(__file__)), '3MCWB', 'workgroups', workgroup_id)\nsecondary_pic_dir = os.path.join(os.path.dirname(os.path.abspath(__file__)), '3MCWB', 'pic')\n\nprint(f\"[DEBUG] workgroup_id={workgroup_id}\")\nprint(f\"[DEBUG] primary_pic_dir={primary_pic_dir}\")\nprint(f\"[DEBUG] secondary_pic_dir={secondary_pic_dir}\")\n\ndef find_image_click(image_name, wait_time=1):\n    image_path = None\n    path1 = os.path.join(primary_pic_dir, image_name)\n    print(f\"[DEBUG] path1={path1}, exists={os.path.exists(path1)}\")\n    if os.path.exists(path1):\n        image_path = path1\n        print(f\"[图片查找] 找到文件: {path1}\")\n    if not image_path:\n        path2 = os.path.join(secondary_pic_dir, image_name)\n        print(f\"[DEBUG] path2={path2}, exists={os.path.exists(path2)}\")\n        if os.path.exists(path2):\n            image_path = path2\n            print(f\"[图片查找] 找到文件(备用路径): {path2}\")\n    if not image_path:\n        print(f\"[图片查找] 未找到图片: {image_name}\")\n        return False\n    print(f'[图片查找] 查找图片: {image_name}')\n    screenshot = pyautogui.screenshot()\n    screen_np = np.array(screenshot)\n    screen_cv2 = cv2.cvtColor(screen_np, cv2.COLOR_RGB2BGR)\n    template = cv2.imread(image_path)\n    if template is None:\n        print(f'[图片查找] 无法读取图片: {image_name}')\n        return False\n    result = cv2.matchTemplate(screen_cv2, template, cv2.TM_CCOEFF_NORMED)\n    min_val, max_val, min_loc, max_loc = cv2.minMaxLoc(result)\n    if max_val >= 0.8:\n        h, w = template.shape[:2]\n        center_x = max_loc[0] + w // 2\n        center_y = max_loc[1] + h // 2\n        print(f'[图片查找] 找到图片 {image_name}，坐标: ({center_x}, {center_y})')\n        pyautogui.click(center_x, center_y)\n        print(f'[图片查找] 点击坐标: ({center_x}, {center_y})')\n        if wait_time > 0:\n            print(f'[图片查找] 等待 {wait_time} 秒...')\n            time.sleep(wait_time)\n        return True\n    else:\n        print(f'[图片查找] 未找到图片 {image_name}，相似度: {max_val:.3f}')\n        return False\n\nfound_any = find_image_click('1-ST.png', 0) or find_image_click('1-FD.png', 0) or find_image_click('1-HC.png', 0)\n\nif found_any:\n    print(\"[条件成立] 找到1-ST/1-FD/1-HC图片，执行2.1-2.36操作\")\n    print(\"[2.1] 点击坐标36,522\")\n    pyautogui.click(36, 522)\n    time.sleep(1)\n    print(\"[2.2] 等待1秒\")\n    print(\"[2.3] 点击坐标36,522\")\n    pyautogui.click(36, 522)\n    time.sleep(1)\n    print(\"[2.4] 等待1秒\")\n    print(\"[2.5] 点击坐标36,522\")\n    pyautogui.click(36, 522)\n    time.sleep(1)\n    print(\"[2.6] 等待1秒\")\n    print(\"[2.7] 点击坐标36,522\")\n    pyautogui.click(36, 522)\n    time.sleep(1)\n    print(\"[2.8] 等待1秒\")\n    print(\"[2.9] 点击坐标36,522\")\n    pyautogui.click(36, 522)\n    time.sleep(1)\n    print(\"[2.10] 等待1秒\")\n    print(\"[2.11] 点击坐标36,522\")\n    pyautogui.click(36, 522)\n    time.sleep(1)\n    print(\"[2.12] 等待1秒\")\n    print(\"[2.13] 点击坐标955,715\")\n    pyautogui.click(955, 715)\n    time.sleep(1)\n    print(\"[2.14] 等待1秒\")\n    print(f\"[键盘输入] 使用pynput.keyboard输入参数: {coord_params}\")\n    from pynput.keyboard import Controller\n    kb = Controller()\n    kb.type(coord_params)\n    time.sleep(1)\n    print(\"[2.21] 点击坐标1240,708\")\n    pyautogui.click(1240, 708)\n    time.sleep(1)\n    print(\"[2.22] 等待1秒\")\n    print(\"[2.23] 点击坐标1158,718\")\n    pyautogui.click(1158, 718)\n    time.sleep(2)\n    print(\"[2.24] 等待2秒\")\n    print(\"[2.25] 点击坐标666,386\")\n    pyautogui.click(666, 386)\n    time.sleep(1)\n    print(\"[2.26] 等待1秒\")\n    find_image_click('8-ZS.png', 1)\n    time.sleep(1)\n    find_image_click('8-ZS.png', 1)\n    time.sleep(1)\n    print(\"[2.32] 等待1秒\")\n    if find_image_click('1-CZ.png', 1):\n        print(\"[标记] 已找到1-CZ.png并点击，命令执行成功，退出脚本\")\n        print(\"=\"*50)\n        print(\"【模块】执行完成!\")\n        print(\"=\"*50)\n        raise SystemExit(0)\n    time.sleep(1)\n    print(\"[2.34] 等待1秒\")\n    if find_image_click('1-CZ.png', 1):\n        print(\"[标记] 已找到1-CZ.png并点击，命令执行成功，退出脚本\")\n        print(\"=\"*50)\n        print(\"【模块】执行完成!\")\n        print(\"=\"*50)\n        raise SystemExit(0)\n    time.sleep(1)\n    print(\"[2.34] 等待1秒\")\nelse:\n    print(\"[条件不成立] 未找到1-ST/1-FD/1-HC图片，执行2.37-2.43操作\")\n    print(\"[2.37] 点击坐标67,700\")\n    pyautogui.click(67, 700)\n    time.sleep(2)\n    print(\"[2.38] 等待2秒\")\n    find_image_click('1-TC.png', 4)\n    time.sleep(1)\n    print(\"[2.40] 等待1秒\")\n    find_image_click('1-TC.png', 1)\n    time.sleep(1)\n    print(\"[2.42] 等待1秒\")\n    find_image_click('1-CC.png', 4)\n\nprint(\"=\"*50)\nprint(\"【模块】执行完成!\")\nprint(\"=\"*50)",
    "template": {
      "coords": [
        {
          "x": 0,
          "y": 0,
          "label": "坐标1"
        }
      ],
      "workflows": [],
      "exec_mode": "immediate"
    }
  },
  "预约": {
    "type": "python_script",
    "description": "预约：点击指定坐标并执行工作流",
    "has_multi_coords": false,
    "has_auto_input": false,
    "is_python_template": true,
    "python_code": "import os\nimport time\nimport pyautogui\nimport numpy as np\nimport cv2\n\nprint(\"=\"*50)\nprint(\"【预约模块】开始执行\")\nprint(\"=\"*50)\n\nworkgroup_id = '{{workgroup_id}}'\ncoord_params = '{{coord_params}}'\n\nprimary_pic_dir = os.path.join(os.path.dirname(os.path.abspath(__file__)), '3MCWB', 'workgroups', workgroup_id)\nsecondary_pic_dir = os.path.join(os.path.dirname(os.path.abspath(__file__)), '3MCWB', 'pic')\n\nprint(f\"[DEBUG] workgroup_id={workgroup_id}\")\nprint(f\"[DEBUG] primary_pic_dir={primary_pic_dir}\")\nprint(f\"[DEBUG] secondary_pic_dir={secondary_pic_dir}\")\n\ndef find_image_click(image_name, wait_time=1):\n    image_path = None\n    path1 = os.path.join(primary_pic_dir, image_name)\n    print(f\"[DEBUG] path1={path1}, exists={os.path.exists(path1)}\")\n    if os.path.exists(path1):\n        image_path = path1\n        print(f\"[图片查找] 找到文件: {path1}\")\n    if not image_path:\n        path2 = os.path.join(secondary_pic_dir, image_name)\n        print(f\"[DEBUG] path2={path2}, exists={os.path.exists(path2)}\")\n        if os.path.exists(path2):\n            image_path = path2\n            print(f\"[图片查找] 找到文件(备用路径): {path2}\")\n    if not image_path:\n        print(f\"[图片查找] 未找到图片: {image_name}\")\n        return False\n    print(f'[图片查找] 查找图片: {image_name}')\n    screenshot = pyautogui.screenshot()\n    screen_np = np.array(screenshot)\n    screen_cv2 = cv2.cvtColor(screen_np, cv2.COLOR_RGB2BGR)\n    template = cv2.imread(image_path)\n    if template is None:\n        print(f'[图片查找] 无法读取图片: {image_name}')\n        return False\n    result = cv2.matchTemplate(screen_cv2, template, cv2.TM_CCOEFF_NORMED)\n    min_val, max_val, min_loc, max_loc = cv2.minMaxLoc(result)\n    if max_val >= 0.8:\n        h, w = template.shape[:2]\n        center_x = max_loc[0] + w // 2\n        center_y = max_loc[1] + h // 2\n        print(f'[图片查找] 找到图片 {image_name}，坐标: ({center_x}, {center_y})')\n        pyautogui.click(center_x, center_y)\n        print(f'[图片查找] 点击坐标: ({center_x}, {center_y})')\n        if wait_time > 0:\n            print(f'[图片查找] 等待 {wait_time} 秒...')\n            time.sleep(wait_time)\n        return True\n    else:\n        print(f'[图片查找] 未找到图片 {image_name}，相似度: {max_val:.3f}')\n        return False\n\nfound_any = find_image_click('1-ST.png', 0) or find_image_click('1-FD.png', 0) or find_image_click('1-HC.png', 0)\n\nif found_any:\n    print(\"[条件成立] 找到1-ST/1-FD/1-HC图片，执行2.1-2.36操作\")\n    print(\"[2.1] 点击坐标36,522\")\n    pyautogui.click(36, 522)\n    time.sleep(1)\n    print(\"[2.2] 等待1秒\")\n    print(\"[2.3] 点击坐标36,522\")\n    pyautogui.click(36, 522)\n    time.sleep(1)\n    print(\"[2.4] 等待1秒\")\n    print(\"[2.5] 点击坐标36,522\")\n    pyautogui.click(36, 522)\n    time.sleep(1)\n    print(\"[2.6] 等待1秒\")\n    print(\"[2.7] 点击坐标36,522\")\n    pyautogui.click(36, 522)\n    time.sleep(1)\n    print(\"[2.8] 等待1秒\")\n    print(\"[2.9] 点击坐标36,522\")\n    pyautogui.click(36, 522)\n    time.sleep(1)\n    print(\"[2.10] 等待1秒\")\n    print(\"[2.11] 点击坐标36,522\")\n    pyautogui.click(36, 522)\n    time.sleep(1)\n    print(\"[2.12] 等待1秒\")\n    print(\"[2.13] 点击坐标955,715\")\n    pyautogui.click(955, 715)\n    time.sleep(1)\n    print(\"[2.14] 等待1秒\")\n    print(f\"[键盘输入] 使用pynput.keyboard输入参数: {coord_params}\")\n    from pynput.keyboard import Controller\n    kb = Controller()\n    kb.type(coord_params)\n    time.sleep(1)\n    print(\"[2.21] 点击坐标1240,708\")\n    pyautogui.click(1240, 708)\n    time.sleep(1)\n    print(\"[2.22] 等待1秒\")\n    print(\"[2.23] 点击坐标1158,718\")\n    pyautogui.click(1158, 718)\n    time.sleep(2)\n    print(\"[2.24] 等待2秒\")\n    print(\"[2.25] 点击坐标666,386\")\n    pyautogui.click(666, 386)\n    time.sleep(1)\n    print(\"[2.26] 等待1秒\")\n    find_image_click('8-ZS.png', 1)\n    time.sleep(1)\n    find_image_click('8-ZS.png', 1)\n    time.sleep(1)\n    print(\"[2.32] 等待1秒\")\n    if find_image_click('1-CZ.png', 1):\n        print(\"[标记] 已找到1-CZ.png并点击，命令执行成功，退出脚本\")\n        print(\"=\"*50)\n        print(\"【模块】执行完成!\")\n        print(\"=\"*50)\n        raise SystemExit(0)\n    time.sleep(1)\n    print(\"[2.34] 等待1秒\")\n    if find_image_click('1-CZ.png', 1):\n        print(\"[标记] 已找到1-CZ.png并点击，命令执行成功，退出脚本\")\n        print(\"=\"*50)\n        print(\"【模块】执行完成!\")\n        print(\"=\"*50)\n        raise SystemExit(0)\n    time.sleep(1)\n    print(\"[2.34] 等待1秒\")\nelse:\n    print(\"[条件不成立] 未找到1-ST/1-FD/1-HC图片，执行2.37-2.43操作\")\n    print(\"[2.37] 点击坐标67,700\")\n    pyautogui.click(67, 700)\n    time.sleep(2)\n    print(\"[2.38] 等待2秒\")\n    find_image_click('1-TC.png', 4)\n    time.sleep(1)\n    print(\"[2.40] 等待1秒\")\n    find_image_click('1-TC.png', 1)\n    time.sleep(1)\n    print(\"[2.42] 等待1秒\")\n    find_image_click('1-CC.png', 4)\n\nprint(\"=\"*50)\nprint(\"【模块】执行完成!\")\nprint(\"=\"*50)",
    "template": {
      "coords": [
        {
          "x": 0,
          "y": 0,
          "label": "坐标1"
        }
      ],
      "workflows": [],
      "exec_mode": "immediate"
    }
  },
  "集结": {
    "type": "python_script",
    "description": "集结：点击指定坐标并执行工作流",
    "has_multi_coords": false,
    "has_auto_input": false,
    "is_python_template": true,
    "python_code": "import os\nimport time\nimport pyautogui\nimport numpy as np\nimport cv2\n\nprint(\"=\"*50)\nprint(\"【集结模块】开始执行\")\nprint(\"=\"*50)\n\nworkgroup_id = '{{workgroup_id}}'\ncoord_params = '{{coord_params}}'\n\nprimary_pic_dir = os.path.join(os.path.dirname(os.path.abspath(__file__)), '3MCWB', 'workgroups', workgroup_id)\nsecondary_pic_dir = os.path.join(os.path.dirname(os.path.abspath(__file__)), '3MCWB', 'pic')\n\nprint(f\"[DEBUG] workgroup_id={workgroup_id}\")\nprint(f\"[DEBUG] primary_pic_dir={primary_pic_dir}\")\nprint(f\"[DEBUG] secondary_pic_dir={secondary_pic_dir}\")\n\ndef find_image_click(image_name, wait_time=1):\n    image_path = None\n    path1 = os.path.join(primary_pic_dir, image_name)\n    print(f\"[DEBUG] path1={path1}, exists={os.path.exists(path1)}\")\n    if os.path.exists(path1):\n        image_path = path1\n        print(f\"[图片查找] 找到文件: {path1}\")\n    if not image_path:\n        path2 = os.path.join(secondary_pic_dir, image_name)\n        print(f\"[DEBUG] path2={path2}, exists={os.path.exists(path2)}\")\n        if os.path.exists(path2):\n            image_path = path2\n            print(f\"[图片查找] 找到文件(备用路径): {path2}\")\n    if not image_path:\n        print(f\"[图片查找] 未找到图片: {image_name}\")\n        return False\n    print(f'[图片查找] 查找图片: {image_name}')\n    screenshot = pyautogui.screenshot()\n    screen_np = np.array(screenshot)\n    screen_cv2 = cv2.cvtColor(screen_np, cv2.COLOR_RGB2BGR)\n    template = cv2.imread(image_path)\n    if template is None:\n        print(f'[图片查找] 无法读取图片: {image_name}')\n        return False\n    result = cv2.matchTemplate(screen_cv2, template, cv2.TM_CCOEFF_NORMED)\n    min_val, max_val, min_loc, max_loc = cv2.minMaxLoc(result)\n    if max_val >= 0.8:\n        h, w = template.shape[:2]\n        center_x = max_loc[0] + w // 2\n        center_y = max_loc[1] + h // 2\n        print(f'[图片查找] 找到图片 {image_name}，坐标: ({center_x}, {center_y})')\n        pyautogui.click(center_x, center_y)\n        print(f'[图片查找] 点击坐标: ({center_x}, {center_y})')\n        if wait_time > 0:\n            print(f'[图片查找] 等待 {wait_time} 秒...')\n            time.sleep(wait_time)\n        return True\n    else:\n        print(f'[图片查找] 未找到图片 {image_name}，相似度: {max_val:.3f}')\n        return False\n\nfound_any = find_image_click('1-ST.png', 0) or find_image_click('1-FD.png', 0) or find_image_click('1-HC.png', 0)\n\nif found_any:\n    print(\"[条件成立] 找到1-ST/1-FD/1-HC图片，执行2.1-2.36操作\")\n    print(\"[2.1] 点击坐标36,522\")\n    pyautogui.click(36, 522)\n    time.sleep(1)\n    print(\"[2.2] 等待1秒\")\n    print(\"[2.3] 点击坐标36,522\")\n    pyautogui.click(36, 522)\n    time.sleep(1)\n    print(\"[2.4] 等待1秒\")\n    print(\"[2.5] 点击坐标36,522\")\n    pyautogui.click(36, 522)\n    time.sleep(1)\n    print(\"[2.6] 等待1秒\")\n    print(\"[2.7] 点击坐标36,522\")\n    pyautogui.click(36, 522)\n    time.sleep(1)\n    print(\"[2.8] 等待1秒\")\n    print(\"[2.9] 点击坐标36,522\")\n    pyautogui.click(36, 522)\n    time.sleep(1)\n    print(\"[2.10] 等待1秒\")\n    print(\"[2.11] 点击坐标36,522\")\n    pyautogui.click(36, 522)\n    time.sleep(1)\n    print(\"[2.12] 等待1秒\")\n    print(\"[2.13] 点击坐标955,715\")\n    pyautogui.click(955, 715)\n    time.sleep(1)\n    print(\"[2.14] 等待1秒\")\n    print(f\"[键盘输入] 使用pynput.keyboard输入参数: {coord_params}\")\n    from pynput.keyboard import Controller\n    kb = Controller()\n    kb.type(coord_params)\n    time.sleep(1)\n    print(\"[2.21] 点击坐标1240,708\")\n    pyautogui.click(1240, 708)\n    time.sleep(1)\n    print(\"[2.22] 等待1秒\")\n    print(\"[2.23] 点击坐标1158,718\")\n    pyautogui.click(1158, 718)\n    time.sleep(2)\n    print(\"[2.24] 等待2秒\")\n    print(\"[2.25] 点击坐标666,386\")\n    pyautogui.click(666, 386)\n    time.sleep(1)\n    print(\"[2.26] 等待1秒\")\n    find_image_click('8-ZS.png', 1)\n    time.sleep(1)\n    find_image_click('8-ZS.png', 1)\n    time.sleep(1)\n    print(\"[2.32] 等待1秒\")\n    if find_image_click('1-CZ.png', 1):\n        print(\"[标记] 已找到1-CZ.png并点击，命令执行成功，退出脚本\")\n        print(\"=\"*50)\n        print(\"【模块】执行完成!\")\n        print(\"=\"*50)\n        raise SystemExit(0)\n    time.sleep(1)\n    print(\"[2.34] 等待1秒\")\n    if find_image_click('1-CZ.png', 1):\n        print(\"[标记] 已找到1-CZ.png并点击，命令执行成功，退出脚本\")\n        print(\"=\"*50)\n        print(\"【模块】执行完成!\")\n        print(\"=\"*50)\n        raise SystemExit(0)\n    time.sleep(1)\n    print(\"[2.34] 等待1秒\")\nelse:\n    print(\"[条件不成立] 未找到1-ST/1-FD/1-HC图片，执行2.37-2.43操作\")\n    print(\"[2.37] 点击坐标67,700\")\n    pyautogui.click(67, 700)\n    time.sleep(2)\n    print(\"[2.38] 等待2秒\")\n    find_image_click('1-TC.png', 4)\n    time.sleep(1)\n    print(\"[2.40] 等待1秒\")\n    find_image_click('1-TC.png', 1)\n    time.sleep(1)\n    print(\"[2.42] 等待1秒\")\n    find_image_click('1-CC.png', 4)\n\nprint(\"=\"*50)\nprint(\"【模块】执行完成!\")\nprint(\"=\"*50)",
    "template": {
      "coords": [
        {
          "x": 0,
          "y": 0,
          "label": "坐标1"
        }
      ],
      "workflows": [],
      "exec_mode": "immediate"
    }
  },
  "集火": {
    "type": "python_script",
    "description": "集火：点击坐标并自动输入坐标参数",
    "has_multi_coords": false,
    "has_auto_input": true,
    "is_python_template": true,
    "python_code": "import os\nimport time\nimport pyautogui\nimport numpy as np\nimport cv2\n\nprint(\"=\"*50)\nprint(\"【集火模块】开始执行\")\nprint(\"=\"*50)\n\nworkgroup_id = '{{workgroup_id}}'\ncoord_params = '{{coord_params}}'\n\nprimary_pic_dir = os.path.join(os.path.dirname(os.path.abspath(__file__)), '3MCWB', 'workgroups', workgroup_id)\nsecondary_pic_dir = os.path.join(os.path.dirname(os.path.abspath(__file__)), '3MCWB', 'pic')\n\nprint(f\"[DEBUG] workgroup_id={workgroup_id}\")\nprint(f\"[DEBUG] primary_pic_dir={primary_pic_dir}\")\nprint(f\"[DEBUG] secondary_pic_dir={secondary_pic_dir}\")\n\ndef find_image_click(image_name, wait_time=1):\n    image_path = None\n    path1 = os.path.join(primary_pic_dir, image_name)\n    print(f\"[DEBUG] path1={path1}, exists={os.path.exists(path1)}\")\n    if os.path.exists(path1):\n        image_path = path1\n        print(f\"[图片查找] 找到文件: {path1}\")\n    if not image_path:\n        path2 = os.path.join(secondary_pic_dir, image_name)\n        print(f\"[DEBUG] path2={path2}, exists={os.path.exists(path2)}\")\n        if os.path.exists(path2):\n            image_path = path2\n            print(f\"[图片查找] 找到文件(备用路径): {path2}\")\n    if not image_path:\n        print(f\"[图片查找] 未找到图片: {image_name}\")\n        return False\n    print(f'[图片查找] 查找图片: {image_name}')\n    screenshot = pyautogui.screenshot()\n    screen_np = np.array(screenshot)\n    screen_cv2 = cv2.cvtColor(screen_np, cv2.COLOR_RGB2BGR)\n    template = cv2.imread(image_path)\n    if template is None:\n        print(f'[图片查找] 无法读取图片: {image_name}')\n        return False\n    result = cv2.matchTemplate(screen_cv2, template, cv2.TM_CCOEFF_NORMED)\n    min_val, max_val, min_loc, max_loc = cv2.minMaxLoc(result)\n    if max_val >= 0.8:\n        h, w = template.shape[:2]\n        center_x = max_loc[0] + w // 2\n        center_y = max_loc[1] + h // 2\n        print(f'[图片查找] 找到图片 {image_name}，坐标: ({center_x}, {center_y})')\n        pyautogui.click(center_x, center_y)\n        print(f'[图片查找] 点击坐标: ({center_x}, {center_y})')\n        if wait_time > 0:\n            print(f'[图片查找] 等待 {wait_time} 秒...')\n            time.sleep(wait_time)\n        return True\n    else:\n        print(f'[图片查找] 未找到图片 {image_name}，相似度: {max_val:.3f}')\n        return False\n\nfound_any = find_image_click('1-ST.png', 0) or find_image_click('1-FD.png', 0) or find_image_click('1-HC.png', 0)\n\nif found_any:\n    print(\"[条件成立] 找到1-ST/1-FD/1-HC图片，执行2.1-2.36操作\")\n    print(\"[2.1] 点击坐标36,522\")\n    pyautogui.click(36, 522)\n    time.sleep(1)\n    print(\"[2.2] 等待1秒\")\n    print(\"[2.3] 点击坐标36,522\")\n    pyautogui.click(36, 522)\n    time.sleep(1)\n    print(\"[2.4] 等待1秒\")\n    print(\"[2.5] 点击坐标36,522\")\n    pyautogui.click(36, 522)\n    time.sleep(1)\n    print(\"[2.6] 等待1秒\")\n    print(\"[2.7] 点击坐标36,522\")\n    pyautogui.click(36, 522)\n    time.sleep(1)\n    print(\"[2.8] 等待1秒\")\n    print(\"[2.9] 点击坐标36,522\")\n    pyautogui.click(36, 522)\n    time.sleep(1)\n    print(\"[2.10] 等待1秒\")\n    print(\"[2.11] 点击坐标36,522\")\n    pyautogui.click(36, 522)\n    time.sleep(1)\n    print(\"[2.12] 等待1秒\")\n    print(\"[2.13] 点击坐标955,715\")\n    pyautogui.click(955, 715)\n    time.sleep(1)\n    print(\"[2.14] 等待1秒\")\n    print(f\"[键盘输入] 使用pynput.keyboard输入参数: {coord_params}\")\n    from pynput.keyboard import Controller\n    kb = Controller()\n    kb.type(coord_params)\n    time.sleep(1)\n    print(\"[2.21] 点击坐标1240,708\")\n    pyautogui.click(1240, 708)\n    time.sleep(1)\n    print(\"[2.22] 等待1秒\")\n    print(\"[2.23] 点击坐标1158,718\")\n    pyautogui.click(1158, 718)\n    time.sleep(2)\n    print(\"[2.24] 等待2秒\")\n    print(\"[2.25] 点击坐标666,386\")\n    pyautogui.click(666, 386)\n    time.sleep(1)\n    print(\"[2.26] 等待1秒\")\n    find_image_click('8-ZS.png', 1)\n    time.sleep(1)\n    find_image_click('8-ZS.png', 1)\n    time.sleep(1)\n    print(\"[2.32] 等待1秒\")\n    if find_image_click('1-CZ.png', 1):\n        print(\"[标记] 已找到1-CZ.png并点击，命令执行成功，退出脚本\")\n        print(\"=\"*50)\n        print(\"【模块】执行完成!\")\n        print(\"=\"*50)\n        raise SystemExit(0)\n    time.sleep(1)\n    print(\"[2.34] 等待1秒\")\n    if find_image_click('1-CZ.png', 1):\n        print(\"[标记] 已找到1-CZ.png并点击，命令执行成功，退出脚本\")\n        print(\"=\"*50)\n        print(\"【模块】执行完成!\")\n        print(\"=\"*50)\n        raise SystemExit(0)\n    time.sleep(1)\n    print(\"[2.34] 等待1秒\")\nelse:\n    print(\"[条件不成立] 未找到1-ST/1-FD/1-HC图片，执行2.37-2.43操作\")\n    print(\"[2.37] 点击坐标67,700\")\n    pyautogui.click(67, 700)\n    time.sleep(2)\n    print(\"[2.38] 等待2秒\")\n    find_image_click('1-TC.png', 4)\n    time.sleep(1)\n    print(\"[2.40] 等待1秒\")\n    find_image_click('1-TC.png', 1)\n    time.sleep(1)\n    print(\"[2.42] 等待1秒\")\n    find_image_click('1-CC.png', 4)\n\nprint(\"=\"*50)\nprint(\"【模块】执行完成!\")\nprint(\"=\"*50)",
    "template": {
      "coords": [
        {
          "x": 0,
          "y": 0,
          "label": "坐标1"
        }
      ],
      "workflows": [],
      "exec_mode": "immediate"
    }
  },
  "攻城": {
    "type": "python_script",
    "description": "攻城：点击坐标并自动输入坐标参数",
    "has_multi_coords": false,
    "has_auto_input": true,
    "is_python_template": true,
    "python_code": "import os\nimport time\nimport pyautogui\nimport numpy as np\nimport cv2\n\nprint(\"=\"*50)\nprint(\"【攻城模块】开始执行\")\nprint(\"=\"*50)\n\nworkgroup_id = '{{workgroup_id}}'\ncoord_params = '{{coord_params}}'\n\nprimary_pic_dir = os.path.join(os.path.dirname(os.path.abspath(__file__)), '3MCWB', 'workgroups', workgroup_id)\nsecondary_pic_dir = os.path.join(os.path.dirname(os.path.abspath(__file__)), '3MCWB', 'pic')\n\nprint(f\"[DEBUG] workgroup_id={workgroup_id}\")\nprint(f\"[DEBUG] primary_pic_dir={primary_pic_dir}\")\nprint(f\"[DEBUG] secondary_pic_dir={secondary_pic_dir}\")\n\ndef find_image_click(image_name, wait_time=1):\n    image_path = None\n    path1 = os.path.join(primary_pic_dir, image_name)\n    print(f\"[DEBUG] path1={path1}, exists={os.path.exists(path1)}\")\n    if os.path.exists(path1):\n        image_path = path1\n        print(f\"[图片查找] 找到文件: {path1}\")\n    if not image_path:\n        path2 = os.path.join(secondary_pic_dir, image_name)\n        print(f\"[DEBUG] path2={path2}, exists={os.path.exists(path2)}\")\n        if os.path.exists(path2):\n            image_path = path2\n            print(f\"[图片查找] 找到文件(备用路径): {path2}\")\n    if not image_path:\n        print(f\"[图片查找] 未找到图片: {image_name}\")\n        return False\n    print(f'[图片查找] 查找图片: {image_name}')\n    screenshot = pyautogui.screenshot()\n    screen_np = np.array(screenshot)\n    screen_cv2 = cv2.cvtColor(screen_np, cv2.COLOR_RGB2BGR)\n    template = cv2.imread(image_path)\n    if template is None:\n        print(f'[图片查找] 无法读取图片: {image_name}')\n        return False\n    result = cv2.matchTemplate(screen_cv2, template, cv2.TM_CCOEFF_NORMED)\n    min_val, max_val, min_loc, max_loc = cv2.minMaxLoc(result)\n    if max_val >= 0.8:\n        h, w = template.shape[:2]\n        center_x = max_loc[0] + w // 2\n        center_y = max_loc[1] + h // 2\n        print(f'[图片查找] 找到图片 {image_name}，坐标: ({center_x}, {center_y})')\n        pyautogui.click(center_x, center_y)\n        print(f'[图片查找] 点击坐标: ({center_x}, {center_y})')\n        if wait_time > 0:\n            print(f'[图片查找] 等待 {wait_time} 秒...')\n            time.sleep(wait_time)\n        return True\n    else:\n        print(f'[图片查找] 未找到图片 {image_name}，相似度: {max_val:.3f}')\n        return False\n\nfound_any = find_image_click('1-ST.png', 0) or find_image_click('1-FD.png', 0) or find_image_click('1-HC.png', 0)\n\nif found_any:\n    print(\"[条件成立] 找到1-ST/1-FD/1-HC图片，执行2.1-2.36操作\")\n    print(\"[2.1] 点击坐标36,522\")\n    pyautogui.click(36, 522)\n    time.sleep(1)\n    print(\"[2.2] 等待1秒\")\n    print(\"[2.3] 点击坐标36,522\")\n    pyautogui.click(36, 522)\n    time.sleep(1)\n    print(\"[2.4] 等待1秒\")\n    print(\"[2.5] 点击坐标36,522\")\n    pyautogui.click(36, 522)\n    time.sleep(1)\n    print(\"[2.6] 等待1秒\")\n    print(\"[2.7] 点击坐标36,522\")\n    pyautogui.click(36, 522)\n    time.sleep(1)\n    print(\"[2.8] 等待1秒\")\n    print(\"[2.9] 点击坐标36,522\")\n    pyautogui.click(36, 522)\n    time.sleep(1)\n    print(\"[2.10] 等待1秒\")\n    print(\"[2.11] 点击坐标36,522\")\n    pyautogui.click(36, 522)\n    time.sleep(1)\n    print(\"[2.12] 等待1秒\")\n    print(\"[2.13] 点击坐标955,715\")\n    pyautogui.click(955, 715)\n    time.sleep(1)\n    print(\"[2.14] 等待1秒\")\n    print(f\"[键盘输入] 使用pynput.keyboard输入参数: {coord_params}\")\n    from pynput.keyboard import Controller\n    kb = Controller()\n    kb.type(coord_params)\n    time.sleep(1)\n    print(\"[2.21] 点击坐标1240,708\")\n    pyautogui.click(1240, 708)\n    time.sleep(1)\n    print(\"[2.22] 等待1秒\")\n    print(\"[2.23] 点击坐标1158,718\")\n    pyautogui.click(1158, 718)\n    time.sleep(2)\n    print(\"[2.24] 等待2秒\")\n    print(\"[2.25] 点击坐标666,386\")\n    pyautogui.click(666, 386)\n    time.sleep(1)\n    print(\"[2.26] 等待1秒\")\n    find_image_click('8-ZS.png', 1)\n    time.sleep(1)\n    find_image_click('8-ZS.png', 1)\n    time.sleep(1)\n    print(\"[2.32] 等待1秒\")\n    if find_image_click('1-CZ.png', 1):\n        print(\"[标记] 已找到1-CZ.png并点击，命令执行成功，退出脚本\")\n        print(\"=\"*50)\n        print(\"【模块】执行完成!\")\n        print(\"=\"*50)\n        raise SystemExit(0)\n    time.sleep(1)\n    print(\"[2.34] 等待1秒\")\n    if find_image_click('1-CZ.png', 1):\n        print(\"[标记] 已找到1-CZ.png并点击，命令执行成功，退出脚本\")\n        print(\"=\"*50)\n        print(\"【模块】执行完成!\")\n        print(\"=\"*50)\n        raise SystemExit(0)\n    time.sleep(1)\n    print(\"[2.34] 等待1秒\")\nelse:\n    print(\"[条件不成立] 未找到1-ST/1-FD/1-HC图片，执行2.37-2.43操作\")\n    print(\"[2.37] 点击坐标67,700\")\n    pyautogui.click(67, 700)\n    time.sleep(2)\n    print(\"[2.38] 等待2秒\")\n    find_image_click('1-TC.png', 4)\n    time.sleep(1)\n    print(\"[2.40] 等待1秒\")\n    find_image_click('1-TC.png', 1)\n    time.sleep(1)\n    print(\"[2.42] 等待1秒\")\n    find_image_click('1-CC.png', 4)\n\nprint(\"=\"*50)\nprint(\"【模块】执行完成!\")\nprint(\"=\"*50)",
    "template": {
      "coords": [
        {
          "x": 0,
          "y": 0,
          "label": "坐标1"
        }
      ],
      "workflows": [],
      "exec_mode": "immediate"
    }
  },
  "打地": {
    "type": "python_script",
    "description": "打地：按顺序遍历多个坐标并执行工作流",
    "has_multi_coords": true,
    "has_auto_input": true,
    "is_python_template": true,
    "python_code": "import os\nimport time\nimport pyautogui\nimport numpy as np\nimport cv2\n\nprint(\"=\"*50)\nprint(\"【打地模块】开始执行\")\nprint(\"=\"*50)\n\nworkgroup_id = '{{workgroup_id}}'\ncoord_params = '{{coord_params}}'\n\nprimary_pic_dir = os.path.join(os.path.dirname(os.path.abspath(__file__)), '3MCWB', 'workgroups', workgroup_id)\nsecondary_pic_dir = os.path.join(os.path.dirname(os.path.abspath(__file__)), '3MCWB', 'pic')\n\nprint(f\"[DEBUG] workgroup_id={workgroup_id}\")\nprint(f\"[DEBUG] primary_pic_dir={primary_pic_dir}\")\nprint(f\"[DEBUG] secondary_pic_dir={secondary_pic_dir}\")\n\ndef find_image_click(image_name, wait_time=1):\n    image_path = None\n    path1 = os.path.join(primary_pic_dir, image_name)\n    print(f\"[DEBUG] path1={path1}, exists={os.path.exists(path1)}\")\n    if os.path.exists(path1):\n        image_path = path1\n        print(f\"[图片查找] 找到文件: {path1}\")\n    if not image_path:\n        path2 = os.path.join(secondary_pic_dir, image_name)\n        print(f\"[DEBUG] path2={path2}, exists={os.path.exists(path2)}\")\n        if os.path.exists(path2):\n            image_path = path2\n            print(f\"[图片查找] 找到文件(备用路径): {path2}\")\n    if not image_path:\n        print(f\"[图片查找] 未找到图片: {image_name}\")\n        return False\n    print(f'[图片查找] 查找图片: {image_name}')\n    screenshot = pyautogui.screenshot()\n    screen_np = np.array(screenshot)\n    screen_cv2 = cv2.cvtColor(screen_np, cv2.COLOR_RGB2BGR)\n    template = cv2.imread(image_path)\n    if template is None:\n        print(f'[图片查找] 无法读取图片: {image_name}')\n        return False\n    result = cv2.matchTemplate(screen_cv2, template, cv2.TM_CCOEFF_NORMED)\n    min_val, max_val, min_loc, max_loc = cv2.minMaxLoc(result)\n    if max_val >= 0.8:\n        h, w = template.shape[:2]\n        center_x = max_loc[0] + w // 2\n        center_y = max_loc[1] + h // 2\n        print(f'[图片查找] 找到图片 {image_name}，坐标: ({center_x}, {center_y})')\n        pyautogui.click(center_x, center_y)\n        print(f'[图片查找] 点击坐标: ({center_x}, {center_y})')\n        if wait_time > 0:\n            print(f'[图片查找] 等待 {wait_time} 秒...')\n            time.sleep(wait_time)\n        return True\n    else:\n        print(f'[图片查找] 未找到图片 {image_name}，相似度: {max_val:.3f}')\n        return False\n\nfound_any = find_image_click('1-ST.png', 0) or find_image_click('1-FD.png', 0) or find_image_click('1-HC.png', 0)\n\nif found_any:\n    print(\"[条件成立] 找到1-ST/1-FD/1-HC图片，执行2.1-2.36操作\")\n    print(\"[2.1] 点击坐标36,522\")\n    pyautogui.click(36, 522)\n    time.sleep(1)\n    print(\"[2.2] 等待1秒\")\n    print(\"[2.3] 点击坐标36,522\")\n    pyautogui.click(36, 522)\n    time.sleep(1)\n    print(\"[2.4] 等待1秒\")\n    print(\"[2.5] 点击坐标36,522\")\n    pyautogui.click(36, 522)\n    time.sleep(1)\n    print(\"[2.6] 等待1秒\")\n    print(\"[2.7] 点击坐标36,522\")\n    pyautogui.click(36, 522)\n    time.sleep(1)\n    print(\"[2.8] 等待1秒\")\n    print(\"[2.9] 点击坐标36,522\")\n    pyautogui.click(36, 522)\n    time.sleep(1)\n    print(\"[2.10] 等待1秒\")\n    print(\"[2.11] 点击坐标36,522\")\n    pyautogui.click(36, 522)\n    time.sleep(1)\n    print(\"[2.12] 等待1秒\")\n    print(\"[2.13] 点击坐标955,715\")\n    pyautogui.click(955, 715)\n    time.sleep(1)\n    print(\"[2.14] 等待1秒\")\n    print(f\"[键盘输入] 使用pynput.keyboard输入参数: {coord_params}\")\n    from pynput.keyboard import Controller\n    kb = Controller()\n    kb.type(coord_params)\n    time.sleep(1)\n    print(\"[2.21] 点击坐标1240,708\")\n    pyautogui.click(1240, 708)\n    time.sleep(1)\n    print(\"[2.22] 等待1秒\")\n    print(\"[2.23] 点击坐标1158,718\")\n    pyautogui.click(1158, 718)\n    time.sleep(2)\n    print(\"[2.24] 等待2秒\")\n    print(\"[2.25] 点击坐标666,386\")\n    pyautogui.click(666, 386)\n    time.sleep(1)\n    print(\"[2.26] 等待1秒\")\n    find_image_click('8-ZS.png', 1)\n    time.sleep(1)\n    find_image_click('8-ZS.png', 1)\n    time.sleep(1)\n    print(\"[2.32] 等待1秒\")\n    if find_image_click('1-CZ.png', 1):\n        print(\"[标记] 已找到1-CZ.png并点击，命令执行成功，退出脚本\")\n        print(\"=\"*50)\n        print(\"【模块】执行完成!\")\n        print(\"=\"*50)\n        raise SystemExit(0)\n    time.sleep(1)\n    print(\"[2.34] 等待1秒\")\n    if find_image_click('1-CZ.png', 1):\n        print(\"[标记] 已找到1-CZ.png并点击，命令执行成功，退出脚本\")\n        print(\"=\"*50)\n        print(\"【模块】执行完成!\")\n        print(\"=\"*50)\n        raise SystemExit(0)\n    time.sleep(1)\n    print(\"[2.34] 等待1秒\")\nelse:\n    print(\"[条件不成立] 未找到1-ST/1-FD/1-HC图片，执行2.37-2.43操作\")\n    print(\"[2.37] 点击坐标67,700\")\n    pyautogui.click(67, 700)\n    time.sleep(2)\n    print(\"[2.38] 等待2秒\")\n    find_image_click('1-TC.png', 4)\n    time.sleep(1)\n    print(\"[2.40] 等待1秒\")\n    find_image_click('1-TC.png', 1)\n    time.sleep(1)\n    print(\"[2.42] 等待1秒\")\n    find_image_click('1-CC.png', 4)\n\nprint(\"=\"*50)\nprint(\"【模块】执行完成!\")\nprint(\"=\"*50)",
    "template": {
      "coords": [
        {
          "x": 0,
          "y": 0,
          "label": "坐标1"
        },
        {
          "x": 0,
          "y": 0,
          "label": "坐标2"
        }
      ],
      "workflows": [],
      "exec_mode": "immediate"
    }
  },
  "翻红地": {
    "type": "python_script",
    "description": "翻红地",
    "has_multi_coords": true,
    "has_auto_input": false,
    "is_python_template": true,
    "python_code": "import os\nimport time\nimport pyautogui\nimport numpy as np\nimport cv2\n\nprint(\"=\"*50)\nprint(\"【翻红地模块】开始执行\")\nprint(\"=\"*50)\n\nworkgroup_id = '{{workgroup_id}}'\ncoord_params = '{{coord_params}}'\n\nprimary_pic_dir = os.path.join(os.path.dirname(os.path.abspath(__file__)), '3MCWB', 'workgroups', workgroup_id)\nsecondary_pic_dir = os.path.join(os.path.dirname(os.path.abspath(__file__)), '3MCWB', 'pic')\n\nprint(f\"[DEBUG] workgroup_id={workgroup_id}\")\nprint(f\"[DEBUG] primary_pic_dir={primary_pic_dir}\")\nprint(f\"[DEBUG] secondary_pic_dir={secondary_pic_dir}\")\n\ndef find_image_click(image_name, wait_time=1):\n    image_path = None\n    path1 = os.path.join(primary_pic_dir, image_name)\n    print(f\"[DEBUG] path1={path1}, exists={os.path.exists(path1)}\")\n    if os.path.exists(path1):\n        image_path = path1\n        print(f\"[图片查找] 找到文件: {path1}\")\n    if not image_path:\n        path2 = os.path.join(secondary_pic_dir, image_name)\n        print(f\"[DEBUG] path2={path2}, exists={os.path.exists(path2)}\")\n        if os.path.exists(path2):\n            image_path = path2\n            print(f\"[图片查找] 找到文件(备用路径): {path2}\")\n    if not image_path:\n        print(f\"[图片查找] 未找到图片: {image_name}\")\n        return False\n    print(f'[图片查找] 查找图片: {image_name}')\n    screenshot = pyautogui.screenshot()\n    screen_np = np.array(screenshot)\n    screen_cv2 = cv2.cvtColor(screen_np, cv2.COLOR_RGB2BGR)\n    template = cv2.imread(image_path)\n    if template is None:\n        print(f'[图片查找] 无法读取图片: {image_name}')\n        return False\n    result = cv2.matchTemplate(screen_cv2, template, cv2.TM_CCOEFF_NORMED)\n    min_val, max_val, min_loc, max_loc = cv2.minMaxLoc(result)\n    if max_val >= 0.8:\n        h, w = template.shape[:2]\n        center_x = max_loc[0] + w // 2\n        center_y = max_loc[1] + h // 2\n        print(f'[图片查找] 找到图片 {image_name}，坐标: ({center_x}, {center_y})')\n        pyautogui.click(center_x, center_y)\n        print(f'[图片查找] 点击坐标: ({center_x}, {center_y})')\n        if wait_time > 0:\n            print(f'[图片查找] 等待 {wait_time} 秒...')\n            time.sleep(wait_time)\n        return True\n    else:\n        print(f'[图片查找] 未找到图片 {image_name}，相似度: {max_val:.3f}')\n        return False\n\nfound_any = find_image_click('1-ST.png', 0) or find_image_click('1-FD.png', 0) or find_image_click('1-HC.png', 0)\n\nif found_any:\n    print(\"[条件成立] 找到1-ST/1-FD/1-HC图片，执行2.1-2.36操作\")\n    print(\"[2.1] 点击坐标36,522\")\n    pyautogui.click(36, 522)\n    time.sleep(1)\n    print(\"[2.2] 等待1秒\")\n    print(\"[2.3] 点击坐标36,522\")\n    pyautogui.click(36, 522)\n    time.sleep(1)\n    print(\"[2.4] 等待1秒\")\n    print(\"[2.5] 点击坐标36,522\")\n    pyautogui.click(36, 522)\n    time.sleep(1)\n    print(\"[2.6] 等待1秒\")\n    print(\"[2.7] 点击坐标36,522\")\n    pyautogui.click(36, 522)\n    time.sleep(1)\n    print(\"[2.8] 等待1秒\")\n    print(\"[2.9] 点击坐标36,522\")\n    pyautogui.click(36, 522)\n    time.sleep(1)\n    print(\"[2.10] 等待1秒\")\n    print(\"[2.11] 点击坐标36,522\")\n    pyautogui.click(36, 522)\n    time.sleep(1)\n    print(\"[2.12] 等待1秒\")\n    print(\"[2.13] 点击坐标955,715\")\n    pyautogui.click(955, 715)\n    time.sleep(1)\n    print(\"[2.14] 等待1秒\")\n    print(f\"[键盘输入] 使用pynput.keyboard输入参数: {coord_params}\")\n    from pynput.keyboard import Controller\n    kb = Controller()\n    kb.type(coord_params)\n    time.sleep(1)\n    print(\"[2.21] 点击坐标1240,708\")\n    pyautogui.click(1240, 708)\n    time.sleep(1)\n    print(\"[2.22] 等待1秒\")\n    print(\"[2.23] 点击坐标1158,718\")\n    pyautogui.click(1158, 718)\n    time.sleep(2)\n    print(\"[2.24] 等待2秒\")\n    print(\"[2.25] 点击坐标666,386\")\n    pyautogui.click(666, 386)\n    time.sleep(1)\n    print(\"[2.26] 等待1秒\")\n    find_image_click('8-ZS.png', 1)\n    time.sleep(1)\n    find_image_click('8-ZS.png', 1)\n    time.sleep(1)\n    print(\"[2.32] 等待1秒\")\n    if find_image_click('1-CZ.png', 1):\n        print(\"[标记] 已找到1-CZ.png并点击，命令执行成功，退出脚本\")\n        print(\"=\"*50)\n        print(\"【模块】执行完成!\")\n        print(\"=\"*50)\n        raise SystemExit(0)\n    time.sleep(1)\n    print(\"[2.34] 等待1秒\")\n    if find_image_click('1-CZ.png', 1):\n        print(\"[标记] 已找到1-CZ.png并点击，命令执行成功，退出脚本\")\n        print(\"=\"*50)\n        print(\"【模块】执行完成!\")\n        print(\"=\"*50)\n        raise SystemExit(0)\n    time.sleep(1)\n    print(\"[2.34] 等待1秒\")\nelse:\n    print(\"[条件不成立] 未找到1-ST/1-FD/1-HC图片，执行2.37-2.43操作\")\n    print(\"[2.37] 点击坐标67,700\")\n    pyautogui.click(67, 700)\n    time.sleep(2)\n    print(\"[2.38] 等待2秒\")\n    find_image_click('1-TC.png', 4)\n    time.sleep(1)\n    print(\"[2.40] 等待1秒\")\n    find_image_click('1-TC.png', 1)\n    time.sleep(1)\n    print(\"[2.42] 等待1秒\")\n    find_image_click('1-CC.png', 4)\n\nprint(\"=\"*50)\nprint(\"【模块】执行完成!\")\nprint(\"=\"*50)",
    "template": {
      "coords": [
        {
          "x": 0,
          "y": 0,
          "label": "坐标1"
        }
      ],
      "workflows": [],
      "exec_mode": "immediate"
    }
  },
  "铺路": {
    "type": "python_script",
    "description": "铺路：按顺序遍历多个坐标并执行工作流",
    "has_multi_coords": true,
    "has_auto_input": true,
    "is_python_template": true,
    "python_code": "import os\nimport time\nimport pyautogui\nimport numpy as np\nimport cv2\n\nprint(\"=\"*50)\nprint(\"【铺路模块】开始执行\")\nprint(\"=\"*50)\n\nworkgroup_id = '{{workgroup_id}}'\ncoord_params = '{{coord_params}}'\n\nprimary_pic_dir = os.path.join(os.path.dirname(os.path.abspath(__file__)), '3MCWB', 'workgroups', workgroup_id)\nsecondary_pic_dir = os.path.join(os.path.dirname(os.path.abspath(__file__)), '3MCWB', 'pic')\n\nprint(f\"[DEBUG] workgroup_id={workgroup_id}\")\nprint(f\"[DEBUG] primary_pic_dir={primary_pic_dir}\")\nprint(f\"[DEBUG] secondary_pic_dir={secondary_pic_dir}\")\n\ndef find_image_click(image_name, wait_time=1):\n    image_path = None\n    path1 = os.path.join(primary_pic_dir, image_name)\n    print(f\"[DEBUG] path1={path1}, exists={os.path.exists(path1)}\")\n    if os.path.exists(path1):\n        image_path = path1\n        print(f\"[图片查找] 找到文件: {path1}\")\n    if not image_path:\n        path2 = os.path.join(secondary_pic_dir, image_name)\n        print(f\"[DEBUG] path2={path2}, exists={os.path.exists(path2)}\")\n        if os.path.exists(path2):\n            image_path = path2\n            print(f\"[图片查找] 找到文件(备用路径): {path2}\")\n    if not image_path:\n        print(f\"[图片查找] 未找到图片: {image_name}\")\n        return False\n    print(f'[图片查找] 查找图片: {image_name}')\n    screenshot = pyautogui.screenshot()\n    screen_np = np.array(screenshot)\n    screen_cv2 = cv2.cvtColor(screen_np, cv2.COLOR_RGB2BGR)\n    template = cv2.imread(image_path)\n    if template is None:\n        print(f'[图片查找] 无法读取图片: {image_name}')\n        return False\n    result = cv2.matchTemplate(screen_cv2, template, cv2.TM_CCOEFF_NORMED)\n    min_val, max_val, min_loc, max_loc = cv2.minMaxLoc(result)\n    if max_val >= 0.8:\n        h, w = template.shape[:2]\n        center_x = max_loc[0] + w // 2\n        center_y = max_loc[1] + h // 2\n        print(f'[图片查找] 找到图片 {image_name}，坐标: ({center_x}, {center_y})')\n        pyautogui.click(center_x, center_y)\n        print(f'[图片查找] 点击坐标: ({center_x}, {center_y})')\n        if wait_time > 0:\n            print(f'[图片查找] 等待 {wait_time} 秒...')\n            time.sleep(wait_time)\n        return True\n    else:\n        print(f'[图片查找] 未找到图片 {image_name}，相似度: {max_val:.3f}')\n        return False\n\nfound_any = find_image_click('1-ST.png', 0) or find_image_click('1-FD.png', 0) or find_image_click('1-HC.png', 0)\n\nif found_any:\n    print(\"[条件成立] 找到1-ST/1-FD/1-HC图片，执行2.1-2.36操作\")\n    print(\"[2.1] 点击坐标36,522\")\n    pyautogui.click(36, 522)\n    time.sleep(1)\n    print(\"[2.2] 等待1秒\")\n    print(\"[2.3] 点击坐标36,522\")\n    pyautogui.click(36, 522)\n    time.sleep(1)\n    print(\"[2.4] 等待1秒\")\n    print(\"[2.5] 点击坐标36,522\")\n    pyautogui.click(36, 522)\n    time.sleep(1)\n    print(\"[2.6] 等待1秒\")\n    print(\"[2.7] 点击坐标36,522\")\n    pyautogui.click(36, 522)\n    time.sleep(1)\n    print(\"[2.8] 等待1秒\")\n    print(\"[2.9] 点击坐标36,522\")\n    pyautogui.click(36, 522)\n    time.sleep(1)\n    print(\"[2.10] 等待1秒\")\n    print(\"[2.11] 点击坐标36,522\")\n    pyautogui.click(36, 522)\n    time.sleep(1)\n    print(\"[2.12] 等待1秒\")\n    print(\"[2.13] 点击坐标955,715\")\n    pyautogui.click(955, 715)\n    time.sleep(1)\n    print(\"[2.14] 等待1秒\")\n    print(f\"[键盘输入] 使用pynput.keyboard输入参数: {coord_params}\")\n    from pynput.keyboard import Controller\n    kb = Controller()\n    kb.type(coord_params)\n    time.sleep(1)\n    print(\"[2.21] 点击坐标1240,708\")\n    pyautogui.click(1240, 708)\n    time.sleep(1)\n    print(\"[2.22] 等待1秒\")\n    print(\"[2.23] 点击坐标1158,718\")\n    pyautogui.click(1158, 718)\n    time.sleep(2)\n    print(\"[2.24] 等待2秒\")\n    print(\"[2.25] 点击坐标666,386\")\n    pyautogui.click(666, 386)\n    time.sleep(1)\n    print(\"[2.26] 等待1秒\")\n    find_image_click('8-ZS.png', 1)\n    time.sleep(1)\n    find_image_click('8-ZS.png', 1)\n    time.sleep(1)\n    print(\"[2.32] 等待1秒\")\n    if find_image_click('1-CZ.png', 1):\n        print(\"[标记] 已找到1-CZ.png并点击，命令执行成功，退出脚本\")\n        print(\"=\"*50)\n        print(\"【模块】执行完成!\")\n        print(\"=\"*50)\n        raise SystemExit(0)\n    time.sleep(1)\n    print(\"[2.34] 等待1秒\")\n    if find_image_click('1-CZ.png', 1):\n        print(\"[标记] 已找到1-CZ.png并点击，命令执行成功，退出脚本\")\n        print(\"=\"*50)\n        print(\"【模块】执行完成!\")\n        print(\"=\"*50)\n        raise SystemExit(0)\n    time.sleep(1)\n    print(\"[2.34] 等待1秒\")\nelse:\n    print(\"[条件不成立] 未找到1-ST/1-FD/1-HC图片，执行2.37-2.43操作\")\n    print(\"[2.37] 点击坐标67,700\")\n    pyautogui.click(67, 700)\n    time.sleep(2)\n    print(\"[2.38] 等待2秒\")\n    find_image_click('1-TC.png', 4)\n    time.sleep(1)\n    print(\"[2.40] 等待1秒\")\n    find_image_click('1-TC.png', 1)\n    time.sleep(1)\n    print(\"[2.42] 等待1秒\")\n    find_image_click('1-CC.png', 4)\n\nprint(\"=\"*50)\nprint(\"【模块】执行完成!\")\nprint(\"=\"*50)",
    "template": {
      "coords": [
        {
          "x": 0,
          "y": 0,
          "label": "坐标1"
        },
        {
          "x": 0,
          "y": 0,
          "label": "坐标2"
        }
      ],
      "workflows": [],
      "exec_mode": "immediate"
    }
  },
  "驻守": {
    "type": "python_script",
    "description": "驻守：执行Python脚本完成操作",
    "has_multi_coords": false,
    "has_auto_input": true,
    "is_python_template": true,
    "python_code": "import os\nimport time\nimport pyautogui\nimport numpy as np\nimport cv2\n\nprint(\"=\"*50)\nprint(\"【驻守模块】开始执行\")\nprint(\"=\"*50)\n\nworkgroup_id = '{{workgroup_id}}'\ncoord_params = '{{coord_params}}'\n\nprimary_pic_dir = os.path.join(os.path.dirname(os.path.abspath(__file__)), '3MCWB', 'workgroups', workgroup_id)\nsecondary_pic_dir = os.path.join(os.path.dirname(os.path.abspath(__file__)), '3MCWB', 'pic')\n\nprint(f\"[DEBUG] workgroup_id={workgroup_id}\")\nprint(f\"[DEBUG] primary_pic_dir={primary_pic_dir}\")\nprint(f\"[DEBUG] secondary_pic_dir={secondary_pic_dir}\")\n\ndef find_image_click(image_name, wait_time=1):\n    image_path = None\n    path1 = os.path.join(primary_pic_dir, image_name)\n    print(f\"[DEBUG] path1={path1}, exists={os.path.exists(path1)}\")\n    if os.path.exists(path1):\n        image_path = path1\n        print(f\"[图片查找] 找到文件: {path1}\")\n    if not image_path:\n        path2 = os.path.join(secondary_pic_dir, image_name)\n        print(f\"[DEBUG] path2={path2}, exists={os.path.exists(path2)}\")\n        if os.path.exists(path2):\n            image_path = path2\n            print(f\"[图片查找] 找到文件(备用路径): {path2}\")\n    if not image_path:\n        print(f\"[图片查找] 未找到图片: {image_name}\")\n        return False\n    print(f'[图片查找] 查找图片: {image_name}')\n    screenshot = pyautogui.screenshot()\n    screen_np = np.array(screenshot)\n    screen_cv2 = cv2.cvtColor(screen_np, cv2.COLOR_RGB2BGR)\n    template = cv2.imread(image_path)\n    if template is None:\n        print(f'[图片查找] 无法读取图片: {image_name}')\n        return False\n    result = cv2.matchTemplate(screen_cv2, template, cv2.TM_CCOEFF_NORMED)\n    min_val, max_val, min_loc, max_loc = cv2.minMaxLoc(result)\n    if max_val >= 0.8:\n        h, w = template.shape[:2]\n        center_x = max_loc[0] + w // 2\n        center_y = max_loc[1] + h // 2\n        print(f'[图片查找] 找到图片 {image_name}，坐标: ({center_x}, {center_y})')\n        pyautogui.click(center_x, center_y)\n        print(f'[图片查找] 点击坐标: ({center_x}, {center_y})')\n        if wait_time > 0:\n            print(f'[图片查找] 等待 {wait_time} 秒...')\n            time.sleep(wait_time)\n        return True\n    else:\n        print(f'[图片查找] 未找到图片 {image_name}，相似度: {max_val:.3f}')\n        return False\n\nfound_any = find_image_click('1-ST.png', 0) or find_image_click('1-FD.png', 0) or find_image_click('1-HC.png', 0)\n\nif found_any:\n    print(\"[条件成立] 找到1-ST/1-FD/1-HC图片，执行2.1-2.36操作\")\n    print(\"[2.1] 点击坐标36,522\")\n    pyautogui.click(36, 522)\n    time.sleep(1)\n    print(\"[2.2] 等待1秒\")\n    print(\"[2.3] 点击坐标36,522\")\n    pyautogui.click(36, 522)\n    time.sleep(1)\n    print(\"[2.4] 等待1秒\")\n    print(\"[2.5] 点击坐标36,522\")\n    pyautogui.click(36, 522)\n    time.sleep(1)\n    print(\"[2.6] 等待1秒\")\n    print(\"[2.7] 点击坐标36,522\")\n    pyautogui.click(36, 522)\n    time.sleep(1)\n    print(\"[2.8] 等待1秒\")\n    print(\"[2.9] 点击坐标36,522\")\n    pyautogui.click(36, 522)\n    time.sleep(1)\n    print(\"[2.10] 等待1秒\")\n    print(\"[2.11] 点击坐标36,522\")\n    pyautogui.click(36, 522)\n    time.sleep(1)\n    print(\"[2.12] 等待1秒\")\n    print(\"[2.13] 点击坐标955,715\")\n    pyautogui.click(955, 715)\n    time.sleep(1)\n    print(\"[2.14] 等待1秒\")\n    print(f\"[键盘输入] 使用pynput.keyboard输入参数: {coord_params}\")\n    from pynput.keyboard import Controller\n    kb = Controller()\n    kb.type(coord_params)\n    time.sleep(1)\n    print(\"[2.21] 点击坐标1240,708\")\n    pyautogui.click(1240, 708)\n    time.sleep(1)\n    print(\"[2.22] 等待1秒\")\n    print(\"[2.23] 点击坐标1158,718\")\n    pyautogui.click(1158, 718)\n    time.sleep(2)\n    print(\"[2.24] 等待2秒\")\n    print(\"[2.25] 点击坐标666,386\")\n    pyautogui.click(666, 386)\n    time.sleep(1)\n    print(\"[2.26] 等待1秒\")\n    find_image_click('8-ZS.png', 1)\n    time.sleep(1)\n    find_image_click('8-ZS.png', 1)\n    time.sleep(1)\n    print(\"[2.32] 等待1秒\")\n    if find_image_click('1-CZ.png', 1):\n        print(\"[标记] 已找到1-CZ.png并点击，命令执行成功，退出脚本\")\n        print(\"=\"*50)\n        print(\"【模块】执行完成!\")\n        print(\"=\"*50)\n        raise SystemExit(0)\n    time.sleep(1)\n    print(\"[2.34] 等待1秒\")\n    if find_image_click('1-CZ.png', 1):\n        print(\"[标记] 已找到1-CZ.png并点击，命令执行成功，退出脚本\")\n        print(\"=\"*50)\n        print(\"【模块】执行完成!\")\n        print(\"=\"*50)\n        raise SystemExit(0)\n    time.sleep(1)\n    print(\"[2.34] 等待1秒\")\nelse:\n    print(\"[条件不成立] 未找到1-ST/1-FD/1-HC图片，执行2.37-2.43操作\")\n    print(\"[2.37] 点击坐标67,700\")\n    pyautogui.click(67, 700)\n    time.sleep(2)\n    print(\"[2.38] 等待2秒\")\n    find_image_click('1-TC.png', 4)\n    time.sleep(1)\n    print(\"[2.40] 等待1秒\")\n    find_image_click('1-TC.png', 1)\n    time.sleep(1)\n    print(\"[2.42] 等待1秒\")\n    find_image_click('1-CC.png', 4)\n\nprint(\"=\"*50)\nprint(\"【模块】执行完成!\")\nprint(\"=\"*50)",
    "template": {
      "coords": [
        {
          "x": 0,
          "y": 0,
          "label": "坐标参数(格式0.0)"
        }
      ],
      "workflows": [],
      "exec_mode": "immediate"
    }
  }
}